chromark/__init__.py
chromark/main.py
chromark-0.0.4.dist-info/METADATA
chromark-0.0.4.dist-info/WHEEL
chromark-0.0.4.dist-info/entry_points.txt
chromark-0.0.4.dist-info/top_level.txt
chromark-0.0.4.dist-info/RECORD
