Metadata-Version: 2.1
Name: chromark
Version: 0.0.4
Summary: Read chrome bookmark file
Author-email: ken <block24block@gmail.com>
Project-URL: Homepage, https://github.com/turnon/chromark
Classifier: Programming Language :: Python :: 3
Classifier: License :: OSI Approved :: MIT License
Classifier: Operating System :: OS Independent
Requires-Python: >=3.8
